LICENSE
MANIFEST.in
pavement.py
paver-minilib.zip
sendmsg.c
setup.py
sendmsg.egg-info/PKG-INFO
sendmsg.egg-info/SOURCES.txt
sendmsg.egg-info/dependency_links.txt
sendmsg.egg-info/top_level.txt