Metadata-Version: 1.0
Name: sendmsg
Version: 1.0
Summary: send file descriptors over AF_UNIX sockets via sendmsg(2)
Home-page: UNKNOWN
Author: Libor Michalek
Author-email: libor@pobox.com
License: bsd
Platform: UNKNOWN
Classifier: Development Status :: 5 - Production/Stable
Classifier: Intended Audience :: Developers
Classifier: License :: OSI Approved :: BSD License
Classifier: Natural Language :: English
Classifier: Operating System :: Unix
Classifier: Programming Language :: C
Classifier: Topic :: System :: Networking
